{
  "background": "#000000",
  "calendarBackground": "#252423",
  "calendarButtonBorder": "#A19F9D",
  "calendarButtonHover": "#323130",
  "calendarButtonSelected": "#3B3A39",
  "calendarTextDisabled": "#797775",
  "calendarTextHover": "#F3F2F1",
  "calendarTextOutside": "#A19F9D",
  "calendarTextRest": "#F3F2F1",
  "checkBoxCheckedBackground": "#111111",
  "checkBoxCheckedBorder": "#00ffff",
  "checkBoxCheckedDefault": "#6cb8f6",
  "checkBoxCheckedHoverBackground": "#111111",
  "checkBoxCheckedHoverBorder": "#800080",
  "checkBoxDisabledBackground": "#000000",
  "checkBoxDisabledBorder": "#0AFF00",
  "checkBoxIndeterminateCircleBackground": "#ffffff",
  "checkBoxIndeterminateCircleHoverBackground": "#ffffff",
  "checkBoxRestBackground": "#0078D4",
  "checkBoxRestBorder": "#F3F2F1",
  "checkBoxRestCheck": "#ffffff",
  "checkBoxRestFocus": "#ffffff",
  "checkBoxRestHover": "#A19F9D",
  "checkBoxRestHoverText": "#ffffff",
  "choiceGroupCircleHover": "#00ffff",
  "choiceGroupFocus": "#A19F9D",
  "commandBarBorder": "#605E5C",
  "commandBarButtonDisabledColor": "#0AFF00",
  "commandBarButtonHoverBackground": "#00ffff",
  "commandBarButtonHoverColor": "#1b1a19",
  "commandBarButtonHoverIcon": "#000000",
  "commandBarButtonRootColor": "#ffffff",
  "commandBarButtonSelectedBackground": "#00ffff",
  "commandBarButtonSelectedIcon": "#000000",
  "commandBarButtonSelectedHoverBackground": "#00ffff",
  "controlOutlinesAccent": "#00ffff",
  "controlOutlinesBackground": "#111111",
  "controlOutlinesDirty": "#c87fdc",
  "controlOutlinesDisabled": "#5A5A5A",
  "controlOutlinesError": "#f63747",
  "controlOutlinesFocus": "#00ffff",
  "controlOutlinesHover": "#ffffff",
  "controlOutlinesRest": "#ffffff",
  "dangerButtonHoverBackground": "#00ffff",
  "dangerButtonHoverBorder": "#00e8e8",
  "dangerButtonHoverText": "#000000",
  "dangerButtonPressedBackground": "#00e8e8",
  "dangerButtonPressedBorder": "#00e8e8",
  "dangerButtonPressedText": "#1b1a19",
  "dangerButtonRestBackground": "#000000",
  "dangerButtonRestBorder": "#ffffff",
  "dangerButtonRestText": "#ffffff",
  "dataColorDataColor": "#C7D3FF",
  "dataColorNodata": "#747474",
  "datePickerDisabledBorder": "#A19F9D",
  "datePickerRestSelected": "#02FEFF",
  "datePickerRestText": "#000000",
  "detailsRowBorder": "#ffffff",
  "detailsRowFocus": "#00ffff",
  "detailsRowHoveredBackground": "#262626",
  "detailsRowHoveredLink": "#000000",
  "detailsRowHoveredRowLink": "#7bb2fe",
  "detailsRowSelectedHoveredLink": "#7bb2fe",
  "detailsRowSelectedLink": "#FEFF00",
  "disabledButtonBackground": "#F3F2F1",
  "disabledButtonText": "#A19F9D",
  "dropDownBackgroundHover": "#000000",
  "dropDownBackgroundRest": "#1b1a19",
  "dropDownTextHovered": "#ffffff",
  "itemHover": "#00ffff",
  "itemSelect": "#404040",
  "itemSelectHovered": "#404040",
  "primaryButtonDisabledBackground": "#000000",
  "primaryButtonDisabledBorder": "#00FF00",
  "primaryButtonDisabledText": "#00FF00",
  "primaryButtonFocusText": "#ffffff",
  "primaryButtonHoverBackground": "#00ffff",
  "primaryButtonHoverText": "#000000",
  "primaryButtonPressedBackground": "#00ffff",
  "primaryButtonPressedText": "#1b1a19",
  "primaryButtonRestBackground": "#000000",
  "primaryButtonRestBorder": "#ffffff",
  "primaryButtonRestText": "#ffffff",
  "radioButtonCircleBorderDisabled": "#00FF00",
  "radioButtonCircleCheckedDisabled": "#ffffff",
  "radioButtonCircleUncheckedRest": "#ffffff",
  "radioButtonPillCheckedHover": "#6ca9fe",
  "radioButtonPillDisabled": "#00FF00",
  "radioButtonPillUncheckedDisabled": "#00FF00",
  "radioButtonPillUncheckedHover": "#00ffff",
  "secondaryButtonFocusBorder": "#A19F9D",
  "secondaryButtonHoverBackground": "#00ffff",
  "secondaryButtonHoverBorder": "#00e8e8",
  "secondaryButtonHoverColor": "#1b1a19",
  "secondaryButtonPressedBackground": "#00e8e8",
  "secondaryButtonPressedBorder": "#00e8e8",
  "secondaryButtonPressedText": "#1b1a19",
  "secondaryButtonRestBackground": "#000000",
  "secondaryButtonRestBorder": "#ffffff",
  "secondaryButtonRestText": "#ffffff",
  "shimmerPrimary": "#808080",
  "shimmerSecondary": "#404040",
  "sliderActiveBackground": "#605E5C",
  "sliderActiveBackgroundHovered": "#00ffff",
  "sliderActiveBackgroundPressed": "#00ffff",
  "sliderActiveDisabledBackground": "#0AFF00",
  "sliderInactiveBackgroundHovered": "#585858",
  "sliderInactiveDisabledBackground": "#0AFF00",
  "statusBarBackgroundError": "#000000",
  "statusBarBackgroundInformation": "#000000",
  "statusBarBackgroundSuccess": "#000000",
  "statusBarBackgroundUpsell": "#000000",
  "statusBarBackgroundWarning": "#000000",
  "statusBarBorderDefault": "#00245B",
  "statusBarBorderError": "#442726",
  "statusBarBorderInformation": "#00245B",
  "statusBarBorderOkay": "#393D1B",
  "statusBarBorderUpsell": "#38134A",
  "statusBarBorderWarning": "#4F2A0F",
  "statusBarIconDisabled": "#8A8886",
  "statusBarIconError": "#e00b1c",
  "statusBarIconInformation": "#015cda",
  "statusBarIconSuccess": "#57A300",
  "statusBarIconUpsell": "#8a2da5",
  "statusBarIconWarning": "#DB7500",
  "statusBarLinkHover": "#FEFF00",
  "statusBarLinkRest": "#FEFF00",
  "tabsHover": "#252423",
  "tagButtonHoverBackground": "#224866",
  "tagButtonHoverBorder": "#ffffff",
  "tagButtonHoverText": "#ffffff",
  "tagButtonPressedBackground": "#224866",
  "tagButtonPressedBorder": "#4894fe",
  "tagButtonPressedText": "#ffffff",
  "tagButtonRestBackground": "#224866",
  "tagButtonRestBorder": "#000000",
  "tagButtonRestText": "#ffffff",
  "teachingBubbleHoverPrimaryButtonBackground": "#043862",
  "teachingBubbleRestBackground": "#00ffff",
  "teachingBubbleRestBorder": "#00ffff",
  "teachingBubbleRestSecondaryBackround": "#000000",
  "teachingBubbleRestText": "#000000",
  "textBody": "#ffffff",
  "textBodyHovered": "#ffffff",
  "textDisabled": "#0AFF00",
  "textError": "#f63747",
  "textHeading": "#ffffff",
  "textHyperlink": "#FEFF00",
  "textHyperlinkHovered": "#FEFF00",
  "textIcon": "#ffffff",
  "textLabel": "#ffffff",
  "textList": "#ffffff",
  "textPlaceholder": "#0AFF00",
  "textSuccess": "#5db300",
  "textValue": "#ffffff",
  "toggleDisabledBackground": "#484644"
}